src/__init__.py
src/loki.py
src/parse.py
daoc-0.0.1.dist-info/LICENSE
daoc-0.0.1.dist-info/METADATA
daoc-0.0.1.dist-info/WHEEL
daoc-0.0.1.dist-info/entry_points.txt
daoc-0.0.1.dist-info/top_level.txt
daoc-0.0.1.dist-info/RECORD
